xxhash/__init__.py
xxhash/__init__.pyi
xxhash/_xxhash.cpython-312-aarch64-linux-musl.so
xxhash/py.typed
xxhash/version.py
xxhash-3.6.0.dist-info/METADATA
xxhash-3.6.0.dist-info/WHEEL
xxhash-3.6.0.dist-info/top_level.txt
xxhash-3.6.0.dist-info/RECORD
xxhash-3.6.0.dist-info/licenses/LICENSE
